generativellm/__init__.py
generativellm/chat.py
generativellm-0.1.2.dist-info/METADATA
generativellm-0.1.2.dist-info/WHEEL
generativellm-0.1.2.dist-info/top_level.txt
generativellm-0.1.2.dist-info/RECORD
